fluentmock-0.3.3.dist-info/METADATA
fluentmock-0.3.3.dist-info/DESCRIPTION.rst
fluentmock-0.3.3.dist-info/entry_points.txt
fluentmock-0.3.3.dist-info/zip-safe
fluentmock-0.3.3.dist-info/metadata.json
fluentmock-0.3.3.dist-info/top_level.txt
fluentmock-0.3.3.dist-info/WHEEL
fluentmock-0.3.3.dist-info/RECORD
fluentmock/matchers.py
fluentmock/LICENSE.txt
fluentmock/__init__.py
fluentmock/exceptions.py
